qgis_venv_creator/__init__.py
qgis_venv_creator/create_qgis_venv.py
qgis_venv_creator/py.typed
qgis_venv_creator-0.1.0.dist-info/METADATA
qgis_venv_creator-0.1.0.dist-info/WHEEL
qgis_venv_creator-0.1.0.dist-info/entry_points.txt
qgis_venv_creator-0.1.0.dist-info/licenses/LICENSE.txt
qgis_venv_creator-0.1.0.dist-info/RECORD
