Metadata-Version: 2.1
Name: qgis-venv-creator
Version: 0.1.0
Summary: Tool to create a virtual python environment for QGIS plugin development
Project-URL: Documentation, https://github.com/GispoCoding/qgis-venv-creator#readme
Project-URL: Issues, https://github.com/GispoCoding/qgis-venv-creator/issues
Project-URL: Source, https://github.com/GispoCoding/qgis-venv-creator
Author-email: "Gispo Ltd." <info@gispo.fi>
License: MIT License
License-File: LICENSE.txt
Classifier: Development Status :: 4 - Beta
Classifier: Intended Audience :: Developers
Classifier: License :: OSI Approved :: MIT License
Classifier: Operating System :: OS Independent
Classifier: Programming Language :: Python
Classifier: Programming Language :: Python :: 3.8
Classifier: Programming Language :: Python :: 3.9
Classifier: Programming Language :: Python :: 3.10
Classifier: Programming Language :: Python :: 3.11
Classifier: Programming Language :: Python :: 3.12
Classifier: Programming Language :: Python :: Implementation :: CPython
Classifier: Programming Language :: Python :: Implementation :: PyPy
Requires-Python: >=3.8
